{
  "project_info": {
    "project_number": "1030427491069",
    "firebase_url": "https://masquerade-e58a7.firebaseio.com",
    "project_id": "masquerade-e58a7",
    "storage_bucket": "masquerade-e58a7.appspot.com"
  },
  "client": [
    {
      "client_info": {
        "mobilesdk_app_id": "1:1030427491069:android:0d7b9ab6bf0eaa88",
        "android_client_info": {
          "package_name": "com.example.masquerade"
        }
      },
      "oauth_client": [
        {
          "client_id": "1030427491069-fn3qek9ks3gqgrfioufk96554vopd5ba.apps.googleusercontent.com",
          "client_type": 1,
          "android_info": {
            "package_name": "com.example.masquerade",
            "certificate_hash": "e4a143b6146c61f00590bb8e0dce2faa3467de01"
          }
        },
        {
          "client_id": "1030427491069-4beh5q7412ghb4pv3ba8e9jhajvfr3lr.apps.googleusercontent.com",
          "client_type": 1,
          "android_info": {
            "package_name": "com.example.masquerade",
            "certificate_hash": "c0418e3f5da5edd8e1887379e740631f934db64a"
          }
        },
        {
          "client_id": "1030427491069-g2garlf9seq6o72nu5vvksfstt8ujg9j.apps.googleusercontent.com",
          "client_type": 1,
          "android_info": {
            "package_name": "com.example.masquerade",
            "certificate_hash": "9f88dace1a389034d935d99d7f6fd3de9fd8d39f"
          }
        },
        {
          "client_id": "1030427491069-9v3qe2nqrc204pot5tl372apr6j6i8n8.apps.googleusercontent.com",
          "client_type": 1,
          "android_info": {
            "package_name": "com.example.masquerade",
            "certificate_hash": "5d1b01bcffeeef591629d4de2b73b0b52df10eac"
          }
        },
        {
          "client_id": "1030427491069-m0krk6nfj4ffckvmqg18pkiaipj40boo.apps.googleusercontent.com",
          "client_type": 1,
          "android_info": {
            "package_name": "com.example.masquerade",
            "certificate_hash": "c273550b66821c0cc70b0bd914e9fa01c10fd3c5"
          }
        },
        {
          "client_id": "1030427491069-m9f0asovfseip0cqkkik0n7kfukl79gl.apps.googleusercontent.com",
          "client_type": 1,
          "android_info": {
            "package_name": "com.example.masquerade",
            "certificate_hash": "93a65b42446a84a696ed61ff3e66f0ad61b1ecdd"
          }
        },
        {
          "client_id": "1030427491069-m5u3sghhke4ab3tmb1j5dk9ooht1aer0.apps.googleusercontent.com",
          "client_type": 1,
          "android_info": {
            "package_name": "com.example.masquerade",
            "certificate_hash": "652a967bffdd35991e507d5429ea4a1cd2374d89"
          }
        },
        {
          "client_id": "1030427491069-tidt8ig63h76bqs6fq22ri62u1k48s64.apps.googleusercontent.com",
          "client_type": 1,
          "android_info": {
            "package_name": "com.example.masquerade",
            "certificate_hash": "250fefd174e42de256b0bae5de65f8f6a86747a4"
          }
        },
        {
          "client_id": "1030427491069-0hbkeomrdr7s69gr4i17d7165k4vlcf6.apps.googleusercontent.com",
          "client_type": 3
        }
      ],
      "api_key": [
        {
          "current_key": "AIzaSyD3A_2uy9CGz8FHxLOTnjCIAIWCWfSniJU"
        }
      ],
      "services": {
        "appinvite_service": {
          "other_platform_oauth_client": [
            {
              "client_id": "1030427491069-f8bfu9jtbcnkav4a24vj3pisnipslr3s.apps.googleusercontent.com",
              "client_type": 3
            }
          ]
        }
      }
    }
  ],
  "configuration_version": "1"
}